calculator/__init__.py
calculator/__main__.py
calculator/app.py
calculator/operation.py
calculator/utils.py
sat_calculator-0.2.4.dist-info/LICENSE
sat_calculator-0.2.4.dist-info/METADATA
sat_calculator-0.2.4.dist-info/WHEEL
sat_calculator-0.2.4.dist-info/entry_points.txt
sat_calculator-0.2.4.dist-info/top_level.txt
sat_calculator-0.2.4.dist-info/RECORD
