Metadata-Version: 2.1
Name: sat-calculator
Version: 0.2.4
Summary: An ordinary calculator
Author: Muhammad Raihan Satrio
License: MIT License
Keywords: calculator,simple,lite,basic
Classifier: Programming Language :: Python :: 3
Classifier: License :: OSI Approved :: MIT License
Classifier: Operating System :: OS Independent
Requires-Python: >=3.7
License-File: LICENSE
Requires-Dist: InquirerPy (>=0.3.4)
Requires-Dist: pytest (>=7.2.0)
Requires-Dist: click (>=8.1.3)
